refacto/__init__.py
refacto/files_op.py
refacto/find_replace.py
refacto/refacto.py
refacto/utils.py
src/__init__.py
src/files_op.py
src/find_replace.py
src/refacto.py
src/utils.py
refacto-0.0.3.dist-info/LICENSE
refacto-0.0.3.dist-info/METADATA
refacto-0.0.3.dist-info/WHEEL
refacto-0.0.3.dist-info/entry_points.txt
refacto-0.0.3.dist-info/top_level.txt
refacto-0.0.3.dist-info/RECORD
